CHANGES.txt
COPYRIGHT.txt
LICENSE.txt
README.txt
bootstrap.py
buildout.cfg
setup.py
src/zamplugin/__init__.py
src/zamplugin.sitemanager.egg-info/PKG-INFO
src/zamplugin.sitemanager.egg-info/SOURCES.txt
src/zamplugin.sitemanager.egg-info/dependency_links.txt
src/zamplugin.sitemanager.egg-info/namespace_packages.txt
src/zamplugin.sitemanager.egg-info/not-zip-safe
src/zamplugin.sitemanager.egg-info/requires.txt
src/zamplugin.sitemanager.egg-info/top_level.txt
src/zamplugin/sitemanager/README.txt
src/zamplugin/sitemanager/__init__.py
src/zamplugin/sitemanager/app.zcml
src/zamplugin/sitemanager/browser.zcml
src/zamplugin/sitemanager/configure.zcml
src/zamplugin/sitemanager/ftesting.zcml
src/zamplugin/sitemanager/menu.py
src/zamplugin/sitemanager/menu.zcml
src/zamplugin/sitemanager/navigation.py
src/zamplugin/sitemanager/navigation.zcml
src/zamplugin/sitemanager/plugin.py
src/zamplugin/sitemanager/plugin.zcml
src/zamplugin/sitemanager/registration.pt
src/zamplugin/sitemanager/registration.py
src/zamplugin/sitemanager/registration.zcml
src/zamplugin/sitemanager/sitemanager.pt
src/zamplugin/sitemanager/siteregistration.pt
src/zamplugin/sitemanager/tests.py